Metadata-Version: 1.0
Name: samebirthdayrate
Version: 1.0.0
Summary: caculate same birthday rate
Home-page: https://narwelplists.herokuapp.com/
Author: gadfy
Author-email: gadfy_m@163.com
License: MIT Licence
Keywords: pip,samebirthdayrate
Platform: any
